<?xml version="1.0" encoding="UTF-8"?>
<CommandInterface xmlns="http://v8.1c.ru/8.3/xcf/extrnprops" xmlns:xr="http://v8.1c.ru/8.3/xcf/readable" xmlns:xs="http://www.w3.org/2001/XMLSchema" xmlns:xsi="http://www.w3.org/2001/XMLSchema-instance" version="2.15">
	<SubsystemsOrder>
		<Subsystem>d2593ff6-1e64-45d3-8e8a-096652827e65</Subsystem>
		<Subsystem>Subsystem.модульУправленка.Subsystem.сабБюджетирование</Subsystem>
		<Subsystem>Subsystem.модульУправленка.Subsystem.сабБанкИКасса</Subsystem>
		<Subsystem>Subsystem.модульУправленка.Subsystem.сабУправленческийУчет</Subsystem>
		<Subsystem>Subsystem.модульУправленка.Subsystem.сабДокументооборот</Subsystem>
		<Subsystem>969e0932-3303-4a6d-9468-6a23dcf8ba13</Subsystem>
		<Subsystem>553515f7-8933-404a-a659-09671513f0a4</Subsystem>
		<Subsystem>Subsystem.модульУправленка.Subsystem.сабАдминистрированиеУБ</Subsystem>
	</SubsystemsOrder>
</CommandInterface>